.DS_Store
fourtytwo/__init__.py
fourtytwo/bqtools/__init__.py
fourtytwo/bqtools/conversions.py
bqtools-0.6.0.dist-info/LICENSE
bqtools-0.6.0.dist-info/METADATA
bqtools-0.6.0.dist-info/WHEEL
bqtools-0.6.0.dist-info/top_level.txt
bqtools-0.6.0.dist-info/RECORD
