Metadata-Version: 2.1
Name: bqtools
Version: 0.6.0
Summary: Python Tools for BigQuery
Home-page: https://github.com/42DIGITAL/bqtools
Author: Jonathan Rahn
Author-email: jonathan.rahn@42digital.de
License: UNKNOWN
Platform: UNKNOWN
Classifier: Development Status :: 4 - Beta
Classifier: Topic :: Database
Classifier: Programming Language :: Python :: 3
Classifier: License :: OSI Approved :: MIT License
Classifier: Operating System :: OS Independent
Requires-Dist: pandas (>=0.24.0)
Requires-Dist: google-cloud-bigquery (>=1.10.0)
Requires-Dist: python-dateutil (>=2.8.0)
Provides-Extra: test
Requires-Dist: pytest ; extra == 'test'
